transfersh.py
transfersh_cli_config-1.0.3.dist-info/LICENSE
transfersh_cli_config-1.0.3.dist-info/METADATA
transfersh_cli_config-1.0.3.dist-info/WHEEL
transfersh_cli_config-1.0.3.dist-info/entry_points.txt
transfersh_cli_config-1.0.3.dist-info/top_level.txt
transfersh_cli_config-1.0.3.dist-info/RECORD
